venue.S.HTML
apoplast/___itinerary/apoplast.S.HTML
apoplast/___itinerary/book/Vitamin B.S.HTML
apoplast/___itinerary/book/Vitamin K.S.HTML
apoplast/___license/license.s.HTML
apoplast/___license/list/gpl-3.0-standalone.html
apoplast/___license/list/vegan.s.HTML
apoplast/__dictionary/apoplast_1
apoplast/__init__.py
apoplast/__status/API/API_status.proc.py
apoplast/__status/API/db_API/records.json
apoplast/__status/main/DB/records.json
apoplast/__status/main/status.proc.py
apoplast/__status/monetary/db/records.json
apoplast/__status/monetary/essence.py
apoplast/__status/monetary/monetary_monitors/monetary_status_1.py
apoplast/__status/monetary/monetary_status.proc.py
apoplast/__status/monetary/status.S.HTML
apoplast/_ellipses--/__init__.py
apoplast/_essence/__init__.py
apoplast/_essence/essence.S.HTML
apoplast/_ops/clique/__init__.py
apoplast/_ops/monitor.py
apoplast/_ops/off.py
apoplast/_ops/on.py
apoplast/_ops/status.py
apoplast/clouds/affiliates_Amazon/affiliates.s.HTML
apoplast/clouds/clouds.S.HTML
apoplast/clouds/food_USDA/deliveries/one/__init__.py
apoplast/clouds/food_USDA/deliveries/one/assertions/branded.py
apoplast/clouds/food_USDA/deliveries/one/assertions/foundational.py
apoplast/clouds/food_USDA/deliveries/one/status/API_status_branded_1.py
apoplast/clouds/food_USDA/deliveries/one/status/API_status_foundational_1.py
apoplast/clouds/food_USDA/deliveries/source.py
apoplast/clouds/food_USDA/examples/__init__.py
apoplast/clouds/food_USDA/examples/branded/Gardein_f'sh_2663758.JSON
apoplast/clouds/food_USDA/examples/branded/Gardein_f'sh_2664238.JSON
apoplast/clouds/food_USDA/examples/branded/beet_juice_2412474.JSON
apoplast/clouds/food_USDA/examples/branded/beet_juice_2642759.JSON
apoplast/clouds/food_USDA/examples/branded/impossible_beef_2664238.JSON
apoplast/clouds/food_USDA/examples/branded/problems/impossible_2468423.JSON
apoplast/clouds/food_USDA/examples/branded/problems/problems.r.HTML
apoplast/clouds/food_USDA/examples/branded/vegan_pizza_2672996.JSON
apoplast-3.0.7.dist-info/METADATA
apoplast-3.0.7.dist-info/WHEEL
apoplast-3.0.7.dist-info/entry_points.txt
apoplast-3.0.7.dist-info/RECORD
